regressiontesting/__init__.py
regressiontesting/regressiontesting.py
regressiontesting-2.0.0.dist-info/licenses/LICENSE
regressiontesting-2.0.0.dist-info/METADATA
regressiontesting-2.0.0.dist-info/WHEEL
regressiontesting-2.0.0.dist-info/top_level.txt
regressiontesting-2.0.0.dist-info/RECORD
