Metadata-Version: 2.4
Name: regressiontesting
Version: 2.0.0
Summary: A Python package for regression testing with Google Sheets integration.
Home-page: https://github.com/lionelliguo/regressiontesting
Author: Lionel Guo
Author-email: lionelliguo@gmail.com
License: Apache 2.0
Classifier: Programming Language :: Python :: 3
Classifier: License :: OSI Approved :: Apache Software License
Classifier: Operating System :: OS Independent
Requires-Python: >=3.6
License-File: LICENSE
Requires-Dist: gspread
Requires-Dist: google-auth
Requires-Dist: google-auth-oauthlib
Requires-Dist: google-auth-httplib2
Requires-Dist: twine
Dynamic: author
Dynamic: author-email
Dynamic: classifier
Dynamic: description
Dynamic: description-content-type
Dynamic: home-page
Dynamic: license
Dynamic: license-file
Dynamic: requires-dist
Dynamic: requires-python
Dynamic: summary
